[{"traceId":"03d11fd7bbc2d099","id":"03d11fd7bbc2d099","name":"/cart","timestamp":1614738107594000,"duration":383000,"localEndpoint":{"serviceName":"frontend","ipv4":"192.168.1.180"},"tags":{"http.method":"GET","http.url":"http://frontend/cart","load_generator.seq_num":"1082","region":"us-west-1","version":"v125"}},{"traceId":"03d11fd7bbc2d099","parentId":"03d11fd7bbc2d099","id":"d7f448d6555da987","name":"/getcart","timestamp":1614738107689000,"duration":13000,"localEndpoint":{"serviceName":"cartservice","ipv4":"192.168.1.180"},"tags":{"http.method":"GET","http.url":"http://cartservice/GetCart","load_generator.seq_num":"1083","region":"us-east-1","version":"v5"}},{"traceId":"03d11fd7bbc2d099","parentId":"03d11fd7bbc2d099","id":"f6adca9368127175","name":"/getrecommendations","timestamp":1614738107615000,"duration":275000,"localEndpoint":{"serviceName":"recommendationservice","ipv4":"192.168.1.180"},"tags":{"http.method":"GET","http.url":"http://recommendationservice/GetRecommendations","load_generator.seq_num":"1084","region":"us-east-1","version":"v234"}},{"traceId":"03d11fd7bbc2d099","parentId":"f6adca9368127175","id":"c081d3aea0c271be","name":"/getproducts","timestamp":1614738107718000,"duration":28000,"localEndpoint":{"serviceName":"productcatalogservice","ipv4":"192.168.1.180"},"tags":{"http.method":"GET","http.url":"http://productcatalogservice/GetProducts","load_generator.seq_num":"1085","region":"us-east-1","version":"v52"}}]