[{"traceId":"06d964e8ca0f0a33","parentId":"06d964e8ca0f0a33","id":"76c31b3219214a68","name":"/getcart","timestamp":1614738337859000,"duration":119000,"localEndpoint":{"serviceName":"cartservice","ipv4":"192.168.1.180"},"tags":{"http.method":"GET","http.url":"http://cartservice/GetCart","load_generator.seq_num":"6056","region":"us-east-1","version":"v5"}},{"traceId":"06d964e8ca0f0a33","parentId":"1c23545edd99958e","id":"205582903f1022aa","name":"/getproducts","timestamp":1614738338010000,"duration":13000,"localEndpoint":{"serviceName":"productcatalogservice","ipv4":"192.168.1.180"},"tags":{"http.method":"GET","http.url":"http://productcatalogservice/GetProducts","load_generator.seq_num":"6058","region":"us-east-1","version":"v52"}},{"traceId":"06d964e8ca0f0a33","id":"06d964e8ca0f0a33","name":"/cart","timestamp":1614738337844000,"duration":386000,"localEndpoint":{"serviceName":"frontend","ipv4":"192.168.1.180"},"tags":{"http.method":"GET","http.url":"http://frontend/cart","load_generator.seq_num":"6055","region":"us-east-1","version":"v127"}},{"traceId":"06d964e8ca0f0a33","parentId":"06d964e8ca0f0a33","id":"1c23545edd99958e","name":"/getrecommendations","timestamp":1614738337854000,"duration":364000,"localEndpoint":{"serviceName":"recommendationservice","ipv4":"192.168.1.180"},"tags":{"http.method":"GET","http.url":"http://recommendationservice/GetRecommendations","load_generator.seq_num":"6057","region":"us-east-1","version":"v234"}}]