[{"traceId":"11ce53de0585ef34","parentId":"11ce53de0585ef34","id":"d9092a3075e6cc3f","name":"/adrequest","timestamp":1614738701776000,"duration":327000,"localEndpoint":{"serviceName":"adservice","ipv4":"192.168.1.180"},"tags":{"http.method":"GET","http.url":"http://adservice/AdRequest","load_generator.seq_num":"13848"}},{"traceId":"11ce53de0585ef34","parentId":"11ce53de0585ef34","id":"a18017f9a8833529","name":"/getrecommendations","timestamp":1614738701598000,"duration":364000,"localEndpoint":{"serviceName":"recommendationservice","ipv4":"192.168.1.180"},"tags":{"http.method":"GET","http.url":"http://recommendationservice/GetRecommendations","load_generator.seq_num":"13846","region":"us-east-1","version":"v234"}},{"traceId":"11ce53de0585ef34","parentId":"11ce53de0585ef34","id":"0cf0053c006e08ed","name":"/getproducts","timestamp":1614738701677000,"duration":22000,"localEndpoint":{"serviceName":"productcatalogservice","ipv4":"192.168.1.180"},"tags":{"http.method":"GET","http.url":"http://productcatalogservice/GetProducts","load_generator.seq_num":"13845","region":"us-west-1","starter":"squirtle","version":"v52"}},{"traceId":"11ce53de0585ef34","parentId":"a18017f9a8833529","id":"cc851e6ecf7cbb76","name":"/getproducts","timestamp":1614738701744000,"duration":64000,"localEndpoint":{"serviceName":"productcatalogservice","ipv4":"192.168.1.180"},"tags":{"http.method":"GET","http.url":"http://productcatalogservice/GetProducts","load_generator.seq_num":"13847","region":"us-east-1","version":"v52"}},{"traceId":"11ce53de0585ef34","id":"11ce53de0585ef34","name":"/product","timestamp":1614738701593000,"duration":677000,"localEndpoint":{"serviceName":"frontend","ipv4":"192.168.1.180"},"tags":{"http.method":"GET","http.url":"http://frontend/product","load_generator.seq_num":"13844","region":"us-west-1","starter":"squirtle","version":"v125"}}]