[{"traceId":"122f2867afcb405d","parentId":"77b33e8587987430","id":"c5c2595d3ae2f4ae","name":"/getproducts","timestamp":1614738420326000,"duration":78000,"localEndpoint":{"serviceName":"productcatalogservice","ipv4":"192.168.1.180"},"tags":{"http.method":"GET","http.url":"http://productcatalogservice/GetProducts","load_generator.seq_num":"7810","region":"us-east-1","version":"v52"}},{"traceId":"122f2867afcb405d","parentId":"122f2867afcb405d","id":"e87eb35128adf3c7","name":"/getcart","timestamp":1614738420176000,"duration":58000,"localEndpoint":{"serviceName":"cartservice","ipv4":"192.168.1.180"},"tags":{"http.method":"GET","http.url":"http://cartservice/GetCart","load_generator.seq_num":"7808","region":"us-east-1","version":"v5"}},{"traceId":"122f2867afcb405d","id":"122f2867afcb405d","name":"/cart","timestamp":1614738420094000,"duration":446000,"localEndpoint":{"serviceName":"frontend","ipv4":"192.168.1.180"},"tags":{"http.method":"GET","http.url":"http://frontend/cart","load_generator.seq_num":"7807","region":"us-west-1","version":"v125"}},{"traceId":"122f2867afcb405d","parentId":"122f2867afcb405d","id":"77b33e8587987430","name":"/getrecommendations","timestamp":1614738420150000,"duration":302000,"localEndpoint":{"serviceName":"recommendationservice","ipv4":"192.168.1.180"},"tags":{"http.method":"GET","http.url":"http://recommendationservice/GetRecommendations","load_generator.seq_num":"7809","region":"us-east-1","version":"v234"}}]