[{"traceId":"200ee27ae47673b2","id":"200ee27ae47673b2","name":"/cart","timestamp":1614738190594000,"duration":382000,"localEndpoint":{"serviceName":"frontend","ipv4":"192.168.1.180"},"tags":{"http.method":"GET","http.url":"http://frontend/cart","load_generator.seq_num":"2882","region":"us-east-1","version":"v127"}},{"traceId":"200ee27ae47673b2","parentId":"200ee27ae47673b2","id":"003f6fd1d3ac5da1","name":"/getcart","timestamp":1614738190689000,"duration":167000,"localEndpoint":{"serviceName":"cartservice","ipv4":"192.168.1.180"},"tags":{"http.method":"GET","http.url":"http://cartservice/GetCart","load_generator.seq_num":"2883","region":"us-east-1","version":"v5"}},{"traceId":"200ee27ae47673b2","parentId":"200ee27ae47673b2","id":"625773ecc4b697e3","name":"/getrecommendations","timestamp":1614738190657000,"duration":223000,"localEndpoint":{"serviceName":"recommendationservice","ipv4":"192.168.1.180"},"tags":{"http.method":"GET","http.url":"http://recommendationservice/GetRecommendations","load_generator.seq_num":"2884","region":"us-east-1","version":"v234"}},{"traceId":"200ee27ae47673b2","parentId":"625773ecc4b697e3","id":"42a87b6dbf18f516","name":"/getproducts","timestamp":1614738190697000,"duration":46000,"localEndpoint":{"serviceName":"productcatalogservice","ipv4":"192.168.1.180"},"tags":{"http.method":"GET","http.url":"http://productcatalogservice/GetProducts","load_generator.seq_num":"2885","region":"us-east-1","version":"v52"}}]