[{"traceId":"26db7cb61ce8a8ea","id":"26db7cb61ce8a8ea","name":"/cart","timestamp":1614738485844000,"duration":367000,"localEndpoint":{"serviceName":"frontend","ipv4":"192.168.1.180"},"tags":{"http.method":"GET","http.url":"http://frontend/cart","load_generator.seq_num":"9232","region":"us-west-1","version":"v125"}},{"traceId":"26db7cb61ce8a8ea","parentId":"26db7cb61ce8a8ea","id":"d2c66dd76a9c5af7","name":"/getcart","timestamp":1614738485914000,"duration":56000,"localEndpoint":{"serviceName":"cartservice","ipv4":"192.168.1.180"},"tags":{"http.method":"GET","http.url":"http://cartservice/GetCart","load_generator.seq_num":"9233","region":"us-east-1","version":"v5"}},{"traceId":"26db7cb61ce8a8ea","parentId":"c757745d9cd3d791","id":"826b33328a1f58df","name":"/getproducts","timestamp":1614738485961000,"duration":25000,"localEndpoint":{"serviceName":"productcatalogservice","ipv4":"192.168.1.180"},"tags":{"http.method":"GET","http.url":"http://productcatalogservice/GetProducts","load_generator.seq_num":"9235","region":"us-east-1","version":"v52"}},{"traceId":"26db7cb61ce8a8ea","parentId":"26db7cb61ce8a8ea","id":"c757745d9cd3d791","name":"/getrecommendations","timestamp":1614738485893000,"duration":242000,"localEndpoint":{"serviceName":"recommendationservice","ipv4":"192.168.1.180"},"tags":{"http.method":"GET","http.url":"http://recommendationservice/GetRecommendations","load_generator.seq_num":"9234","region":"us-east-1","version":"v234"}}]