[{"traceId":"3669f4dc96c63daf","parentId":"3669f4dc96c63daf","id":"7a7b3cfff3e96ed9","name":"/getcart","timestamp":1614738686663000,"duration":15000,"localEndpoint":{"serviceName":"cartservice","ipv4":"192.168.1.180"},"tags":{"http.method":"GET","http.url":"http://cartservice/GetCart","load_generator.seq_num":"13530","region":"us-east-1","version":"v5"}},{"traceId":"3669f4dc96c63daf","parentId":"3669f4dc96c63daf","id":"04a75c99aad1955c","name":"/getrecommendations","timestamp":1614738686669000,"duration":348000,"localEndpoint":{"serviceName":"recommendationservice","ipv4":"192.168.1.180"},"tags":{"http.method":"GET","http.url":"http://recommendationservice/GetRecommendations","load_generator.seq_num":"13531","region":"us-east-1","version":"v234"}},{"traceId":"3669f4dc96c63daf","parentId":"04a75c99aad1955c","id":"db19d57eb0fe0a5f","name":"/getproducts","timestamp":1614738686752000,"duration":92000,"localEndpoint":{"serviceName":"productcatalogservice","ipv4":"192.168.1.180"},"tags":{"http.method":"GET","http.url":"http://productcatalogservice/GetProducts","load_generator.seq_num":"13532","region":"us-east-1","version":"v52"}},{"traceId":"3669f4dc96c63daf","id":"3669f4dc96c63daf","name":"/cart","timestamp":1614738686594000,"duration":476000,"localEndpoint":{"serviceName":"frontend","ipv4":"192.168.1.180"},"tags":{"http.method":"GET","http.url":"http://frontend/cart","load_generator.seq_num":"13529","region":"us-east-1","version":"v125"}}]