[{"traceId":"550997223f8c4b30","parentId":"550997223f8c4b30","id":"1234d6244fad26ab","name":"/getcart","timestamp":1614738754173000,"duration":190000,"localEndpoint":{"serviceName":"cartservice","ipv4":"192.168.1.180"},"tags":{"http.method":"GET","http.url":"http://cartservice/GetCart","load_generator.seq_num":"14978","region":"us-east-1","version":"v5"}},{"traceId":"550997223f8c4b30","parentId":"550997223f8c4b30","id":"fd6c6a8dad1dac47","name":"/getrecommendations","timestamp":1614738754163000,"duration":226000,"localEndpoint":{"serviceName":"recommendationservice","ipv4":"192.168.1.180"},"tags":{"http.method":"GET","http.url":"http://recommendationservice/GetRecommendations","load_generator.seq_num":"14979","region":"us-east-1","version":"v234"}},{"traceId":"550997223f8c4b30","parentId":"fd6c6a8dad1dac47","id":"3deb074f82f2e50c","name":"/getproducts","timestamp":1614738754350000,"duration":5000,"localEndpoint":{"serviceName":"productcatalogservice","ipv4":"192.168.1.180"},"tags":{"http.method":"GET","http.url":"http://productcatalogservice/GetProducts","load_generator.seq_num":"14980","region":"us-east-1","version":"v52"}},{"traceId":"550997223f8c4b30","id":"550997223f8c4b30","name":"/cart","timestamp":1614738754094000,"duration":334000,"localEndpoint":{"serviceName":"frontend","ipv4":"192.168.1.180"},"tags":{"http.method":"GET","http.url":"http://frontend/cart","load_generator.seq_num":"14977","region":"us-west-1","version":"v125"}}]