[{"traceId":"59e4a135c7485d36","parentId":"59e4a135c7485d36","id":"77a8c624c26f4dec","name":"/adrequest","timestamp":1614738124253000,"duration":268000,"localEndpoint":{"serviceName":"adservice","ipv4":"192.168.1.180"},"tags":{"http.method":"GET","http.url":"http://adservice/AdRequest","load_generator.seq_num":"1435"}},{"traceId":"59e4a135c7485d36","id":"59e4a135c7485d36","name":"/product","timestamp":1614738124093000,"duration":515000,"localEndpoint":{"serviceName":"frontend","ipv4":"192.168.1.180"},"tags":{"http.method":"GET","http.url":"http://frontend/product","load_generator.seq_num":"1431","region":"us-east-1","starter":"bulbasaur","version":"v125"}},{"traceId":"59e4a135c7485d36","parentId":"59e4a135c7485d36","id":"64cb58c37dd621e3","name":"/getrecommendations","timestamp":1614738124284000,"duration":301000,"localEndpoint":{"serviceName":"recommendationservice","ipv4":"192.168.1.180"},"tags":{"http.method":"GET","http.url":"http://recommendationservice/GetRecommendations","load_generator.seq_num":"1433","region":"us-east-1","version":"v234"}},{"traceId":"59e4a135c7485d36","parentId":"59e4a135c7485d36","id":"e3e34a952d4357cf","name":"/getproducts","timestamp":1614738124267000,"duration":73000,"localEndpoint":{"serviceName":"productcatalogservice","ipv4":"192.168.1.180"},"tags":{"http.method":"GET","http.url":"http://productcatalogservice/GetProducts","load_generator.seq_num":"1432","region":"us-east-1","starter":"bulbasaur","version":"v52"}},{"traceId":"59e4a135c7485d36","parentId":"64cb58c37dd621e3","id":"5e0a98227a0e8ef2","name":"/getproducts","timestamp":1614738124443000,"duration":24000,"localEndpoint":{"serviceName":"productcatalogservice","ipv4":"192.168.1.180"},"tags":{"http.method":"GET","http.url":"http://productcatalogservice/GetProducts","load_generator.seq_num":"1434","region":"us-east-1","version":"v52"}}]