[{"traceId":"5b17a9c733eabbe3","id":"5b17a9c733eabbe3","name":"/cart","timestamp":1614738214094000,"duration":303000,"localEndpoint":{"serviceName":"frontend","ipv4":"192.168.1.180"},"tags":{"http.method":"GET","http.url":"http://frontend/cart","load_generator.seq_num":"3385","region":"us-west-1","version":"v125"}},{"traceId":"5b17a9c733eabbe3","parentId":"5b17a9c733eabbe3","id":"eeaafa9dba4194e5","name":"/getcart","timestamp":1614738214143000,"duration":39000,"localEndpoint":{"serviceName":"cartservice","ipv4":"192.168.1.180"},"tags":{"http.method":"GET","http.url":"http://cartservice/GetCart","load_generator.seq_num":"3386","region":"us-east-1","version":"v5"}},{"traceId":"5b17a9c733eabbe3","parentId":"387d34a49237d33c","id":"0ca2dfaa10049d3d","name":"/getproducts","timestamp":1614738214242000,"duration":53000,"localEndpoint":{"serviceName":"productcatalogservice","ipv4":"192.168.1.180"},"tags":{"http.method":"GET","http.url":"http://productcatalogservice/GetProducts","load_generator.seq_num":"3388","region":"us-east-1","version":"v52"}},{"traceId":"5b17a9c733eabbe3","parentId":"5b17a9c733eabbe3","id":"387d34a49237d33c","name":"/getrecommendations","timestamp":1614738214131000,"duration":259000,"localEndpoint":{"serviceName":"recommendationservice","ipv4":"192.168.1.180"},"tags":{"http.method":"GET","http.url":"http://recommendationservice/GetRecommendations","load_generator.seq_num":"3387","region":"us-east-1","version":"v234"}}]