[{"traceId":"5d21f4789a95073a","parentId":"5d21f4789a95073a","id":"317df90ea10d3d70","name":"/getcart","timestamp":1614738718608000,"duration":26000,"localEndpoint":{"serviceName":"cartservice","ipv4":"192.168.1.180"},"tags":{"http.method":"GET","http.url":"http://cartservice/GetCart","load_generator.seq_num":"14212","region":"us-east-1","version":"v5"}},{"traceId":"5d21f4789a95073a","parentId":"6d6e70d2df361d5c","id":"d785f8e4b0cd97f9","name":"/getproducts","timestamp":1614738718718000,"duration":4000,"localEndpoint":{"serviceName":"productcatalogservice","ipv4":"192.168.1.180"},"tags":{"http.method":"GET","http.url":"http://productcatalogservice/GetProducts","load_generator.seq_num":"14214","region":"us-east-1","version":"v52"}},{"traceId":"5d21f4789a95073a","parentId":"5d21f4789a95073a","id":"6d6e70d2df361d5c","name":"/getrecommendations","timestamp":1614738718689000,"duration":131000,"localEndpoint":{"serviceName":"recommendationservice","ipv4":"192.168.1.180"},"tags":{"http.method":"GET","http.url":"http://recommendationservice/GetRecommendations","load_generator.seq_num":"14213","region":"us-east-1","version":"v234"}},{"traceId":"5d21f4789a95073a","id":"5d21f4789a95073a","name":"/cart","timestamp":1614738718594000,"duration":296000,"localEndpoint":{"serviceName":"frontend","ipv4":"192.168.1.180"},"tags":{"http.method":"GET","http.url":"http://frontend/cart","load_generator.seq_num":"14211","region":"us-east-1","version":"v127"}}]