[{"traceId":"63e67a9a39029219","parentId":"63e67a9a39029219","id":"897f099a95902c5d","name":"/adrequest","timestamp":1614738806636000,"duration":439000,"localEndpoint":{"serviceName":"adservice","ipv4":"192.168.1.180"},"tags":{"http.method":"GET","http.url":"http://adservice/AdRequest","load_generator.seq_num":"16111"}},{"traceId":"63e67a9a39029219","parentId":"63e67a9a39029219","id":"e7ae2278209384eb","name":"/getrecommendations","timestamp":1614738806668000,"duration":305000,"localEndpoint":{"serviceName":"recommendationservice","ipv4":"192.168.1.180"},"tags":{"http.method":"GET","http.url":"http://recommendationservice/GetRecommendations","load_generator.seq_num":"16109","region":"us-east-1","version":"v234"}},{"traceId":"63e67a9a39029219","id":"63e67a9a39029219","name":"/product","timestamp":1614738806593000,"duration":572000,"localEndpoint":{"serviceName":"frontend","ipv4":"192.168.1.180"},"tags":{"abandoned-calm-abomasnow":"CVolWSDVzu5ASQgE","abandoned-calm-abra":"7pUalPQzpVFkJgXQ","able-hardy-absol":"Zlqy7BqOOnVKaeJh","absolute-adamant-amoonguss":"MUvWad8QosxFHxlu","absolute-brave-accelgor":"CU37WAdG0VVMlxl9","absolute-calm-abomasnow":"MpYFFcw3QAAnca16","absolute-calm-abra":"GI4XQdt0RqQUZoKG","absolute-calm-accelgor":"dEqe8LTVGeic11mp","absolute-calm-aerodactyl":"ZVdi5w7mjjPnOt9d","absolute-calm-alomomola":"OZHwMQsOJIlcenVm","absolute-calm-ariados":"N25KYy6f5etbrxQA","absolute-impish-accelgor":"ulk5CQdic6DAff9x","absolute-sassy-accelgor":"LpcrjeJ9MI1GBH1V","absolute-sassy-amoonguss":"JTwNBsEOcOMp97yi","absolute-sassy-arcanine":"C7x7WHf31EmT2oB2","absolute-sassy-beldum":"OukhKpSx6Psg3ws2","academic-lax-aggron":"rfl8JQLzHIl1Dnoo","acceptable-hardy-aipom":"0gr4cOw8BPWGXbvv","acceptable-hardy-arcanine":"FuyusXJMuhZAfn2h","acclaimed-bold-absol":"7cvlZGSaHvwWEti0","acidic-hasty-ambipom":"YtTbY0NYtSLdRZTh","acrobatic-careful-aegislash":"lWwW3zO1TzIH3NYQ","acrobatic-sassy-ariados":"4U8lnep1ZGnfKRw1","acrobatic-sassy-aurorus":"weJ7MhrWhXbYijsx","active-sassy-aegislash":"96yogwl3pBLPKuAV","active-sassy-axew":"UQRs7Y2b6iNQsTNE","actual-lax-anorith":"Ibce9xEa6JZMfoYL","actual-sassy-ampharos":"c99Muv3qIHdRt3fD","actual-sassy-bagon":"MUvWad8QosxFHxlu","admirable-bashful-ampharos":"MpYFFcw3QAAnca16","admirable-sassy-arcanine":"HtF4T5uRjH5Udxjm","admirable-sassy-bagon":"RtuvJqw9xaO5vlnQ","adorable-gentle-accelgor":"PxFgnt95WZovt0wc","adored-sassy-accelgor":"aY10JrUYdVTi55eS","adored-sassy-anorith":"tLv1UXWKHGB7m4hA","advanced-sassy-arcanine":"xGotpciTySMIPGxe","adventurous-modest-absol":"0f5B1dSI3680Gd9u","adventurous-modest-amoonguss":"daXEMmUQIlcRuzaR","affectionate-sassy-anorith":"Dw6hPKrF6LuzfjUJ","affectionate-sassy-azumarill":"fzAVILaFyHKwAE2W","aggressive-sassy-amoonguss":"olaXFPbkOuN1FmdA","aggressive-sassy-aron":"SugshSDUv3FNUz3h","aggressive-sassy-aurorus":"iyvsO24ulrzxzt6g","aggressive-sassy-barboach":"MYGf8t8yBFFXouMP","agreeable-sassy-ambipom":"JzkJo6Wt7o8TF51Q","alert-sassy-archeops":"xHhCuQFpHjpTwBHU","ample-sassy-beautifly":"WwmA5NWDB5oa3SV5","angelic-sassy-arcanine":"FozZ7FqT46POLD7O","http.method":"GET","http.url":"http://frontend/product","load_generator.seq_num":"16107","region":"us-east-1","starter":"charmander","version":"v125"}},{"traceId":"63e67a9a39029219","parentId":"63e67a9a39029219","id":"eb17c9d098e59cb5","name":"/getproducts","timestamp":1614738806758000,"duration":46000,"localEndpoint":{"serviceName":"productcatalogservice","ipv4":"192.168.1.180"},"tags":{"http.method":"GET","http.url":"http://productcatalogservice/GetProducts","load_generator.seq_num":"16108","region":"us-east-1","starter":"charmander","version":"v52"}},{"traceId":"63e67a9a39029219","parentId":"e7ae2278209384eb","id":"c4c50d04463fb16f","name":"/getproducts","timestamp":1614738806810000,"duration":23000,"localEndpoint":{"serviceName":"productcatalogservice","ipv4":"192.168.1.180"},"tags":{"http.method":"GET","http.url":"http://productcatalogservice/GetProducts","load_generator.seq_num":"16110","region":"us-east-1","version":"v52"}}]