[{"traceId":"774c0da643658ed5","parentId":"774c0da643658ed5","id":"7aa4f000b02e7742","name":"/getcart","timestamp":1614738847108000,"duration":62000,"localEndpoint":{"serviceName":"cartservice","ipv4":"192.168.1.180"},"tags":{"http.method":"GET","http.url":"http://cartservice/GetCart","load_generator.seq_num":"16983","region":"us-east-1","version":"v5"}},{"traceId":"774c0da643658ed5","parentId":"28b7a622b512df9f","id":"e08b0b540050efea","name":"/getproducts","timestamp":1614738847185000,"duration":75000,"localEndpoint":{"serviceName":"productcatalogservice","ipv4":"192.168.1.180"},"tags":{"http.method":"GET","http.url":"http://productcatalogservice/GetProducts","load_generator.seq_num":"16985","region":"us-east-1","version":"v52"}},{"traceId":"774c0da643658ed5","id":"774c0da643658ed5","name":"/cart","timestamp":1614738847094000,"duration":264000,"localEndpoint":{"serviceName":"frontend","ipv4":"192.168.1.180"},"tags":{"http.method":"GET","http.url":"http://frontend/cart","load_generator.seq_num":"16982","region":"us-east-1","version":"v127"}},{"traceId":"774c0da643658ed5","parentId":"774c0da643658ed5","id":"28b7a622b512df9f","name":"/getrecommendations","timestamp":1614738847103000,"duration":224000,"localEndpoint":{"serviceName":"recommendationservice","ipv4":"192.168.1.180"},"tags":{"http.method":"GET","http.url":"http://recommendationservice/GetRecommendations","load_generator.seq_num":"16984","region":"us-east-1","version":"v234"}}]