[{"traceId":"85b4fa491c4e85fd","parentId":"85b4fa491c4e85fd","id":"88dcfac4d16423ce","name":"/adrequest","timestamp":1614738904251000,"duration":292000,"localEndpoint":{"serviceName":"adservice","ipv4":"192.168.1.180"},"tags":{"http.method":"GET","http.url":"http://adservice/AdRequest","load_generator.seq_num":"18197"}},{"traceId":"85b4fa491c4e85fd","parentId":"85b4fa491c4e85fd","id":"af97efa95eadb54f","name":"/getrecommendations","timestamp":1614738904114000,"duration":258000,"localEndpoint":{"serviceName":"recommendationservice","ipv4":"192.168.1.180"},"tags":{"http.method":"GET","http.url":"http://recommendationservice/GetRecommendations","load_generator.seq_num":"18195","region":"us-east-1","version":"v234"}},{"traceId":"85b4fa491c4e85fd","parentId":"85b4fa491c4e85fd","id":"b222ee00bef5ccf2","name":"/getproducts","timestamp":1614738904172000,"duration":28000,"localEndpoint":{"serviceName":"productcatalogservice","ipv4":"192.168.1.180"},"tags":{"http.method":"GET","http.url":"http://productcatalogservice/GetProducts","load_generator.seq_num":"18194","region":"us-east-1","starter":"squirtle","version":"v52"}},{"traceId":"85b4fa491c4e85fd","parentId":"af97efa95eadb54f","id":"eb1445a431d4f9b7","name":"/getproducts","timestamp":1614738904233000,"duration":80000,"localEndpoint":{"serviceName":"productcatalogservice","ipv4":"192.168.1.180"},"tags":{"http.method":"GET","http.url":"http://productcatalogservice/GetProducts","load_generator.seq_num":"18196","region":"us-east-1","version":"v52"}},{"traceId":"85b4fa491c4e85fd","id":"85b4fa491c4e85fd","name":"/product","timestamp":1614738904093000,"duration":504000,"localEndpoint":{"serviceName":"frontend","ipv4":"192.168.1.180"},"tags":{"http.method":"GET","http.url":"http://frontend/product","load_generator.seq_num":"18193","region":"us-east-1","starter":"squirtle","version":"v127"}}]