[{"traceId":"90adbbde1b6aeb07","id":"90adbbde1b6aeb07","name":"/cart","timestamp":1614740576541000,"duration":420000,"localEndpoint":{"serviceName":"frontend","ipv4":"192.168.1.180"},"tags":{"http.method":"GET","http.url":"http://frontend/cart","load_generator.seq_num":"542","region":"us-west-1","version":"v125"}},{"traceId":"90adbbde1b6aeb07","parentId":"90adbbde1b6aeb07","id":"ed7bccd5be6b9608","name":"/getcart","timestamp":1614740576556000,"duration":52000,"localEndpoint":{"serviceName":"cartservice","ipv4":"192.168.1.180"},"tags":{"http.method":"GET","http.url":"http://cartservice/GetCart","load_generator.seq_num":"543","region":"us-east-1","version":"v5"}},{"traceId":"90adbbde1b6aeb07","parentId":"90adbbde1b6aeb07","id":"62856e4b25d19811","name":"/getrecommendations","timestamp":1614740576623000,"duration":280000,"localEndpoint":{"serviceName":"recommendationservice","ipv4":"192.168.1.180"},"tags":{"http.method":"GET","http.url":"http://recommendationservice/GetRecommendations","load_generator.seq_num":"544","region":"us-east-1","version":"v234"}},{"traceId":"90adbbde1b6aeb07","parentId":"62856e4b25d19811","id":"bb58ddd9db731da3","name":"/getproducts","timestamp":1614740576633000,"duration":195000,"localEndpoint":{"serviceName":"productcatalogservice","ipv4":"192.168.1.180"},"tags":{"http.method":"GET","http.url":"http://productcatalogservice/GetProducts","load_generator.seq_num":"545","region":"us-east-1","version":"v53"}}]