[{"traceId":"941e6066e970360b","id":"941e6066e970360b","name":"/cart","timestamp":1614740600291000,"duration":442000,"localEndpoint":{"serviceName":"frontend","ipv4":"192.168.1.180"},"tags":{"http.method":"GET","http.url":"http://frontend/cart","load_generator.seq_num":"1056","region":"us-west-1","version":"v125"}},{"traceId":"941e6066e970360b","parentId":"941e6066e970360b","id":"02f37801338247c2","name":"/getcart","timestamp":1614740600386000,"duration":120000,"localEndpoint":{"serviceName":"cartservice","ipv4":"192.168.1.180"},"tags":{"http.method":"GET","http.url":"http://cartservice/GetCart","load_generator.seq_num":"1057","region":"us-east-1","version":"v5"}},{"traceId":"941e6066e970360b","parentId":"39ab4c97f4b0f666","id":"bded665e8eb015b6","name":"/getproducts","timestamp":1614740600506000,"duration":85000,"localEndpoint":{"serviceName":"productcatalogservice","ipv4":"192.168.1.180"},"tags":{"http.method":"GET","http.url":"http://productcatalogservice/GetProducts","load_generator.seq_num":"1059","region":"us-east-1","version":"v53"}},{"traceId":"941e6066e970360b","parentId":"941e6066e970360b","id":"39ab4c97f4b0f666","name":"/getrecommendations","timestamp":1614740600379000,"duration":292000,"localEndpoint":{"serviceName":"recommendationservice","ipv4":"192.168.1.180"},"tags":{"http.method":"GET","http.url":"http://recommendationservice/GetRecommendations","load_generator.seq_num":"1058","region":"us-east-1","version":"v234"}}]