[{"traceId":"ac36227855e8695c","parentId":"ac36227855e8695c","id":"dfd2460fb7fa8d79","name":"/getcart","timestamp":1614738458188000,"duration":127000,"localEndpoint":{"serviceName":"cartservice","ipv4":"192.168.1.180"},"tags":{"http.method":"GET","http.url":"http://cartservice/GetCart","load_generator.seq_num":"8629","region":"us-east-1","version":"v5"}},{"traceId":"ac36227855e8695c","parentId":"a70b9cb7da5a8b40","id":"ea193046e0a99049","name":"/getproducts","timestamp":1614738458318000,"duration":63000,"localEndpoint":{"serviceName":"productcatalogservice","ipv4":"192.168.1.180"},"tags":{"http.method":"GET","http.url":"http://productcatalogservice/GetProducts","load_generator.seq_num":"8631","region":"us-east-1","version":"v52"}},{"traceId":"ac36227855e8695c","id":"ac36227855e8695c","name":"/cart","timestamp":1614738458094000,"duration":519000,"localEndpoint":{"serviceName":"frontend","ipv4":"192.168.1.180"},"tags":{"http.method":"GET","http.url":"http://frontend/cart","load_generator.seq_num":"8628","region":"us-west-1","version":"v125"}},{"traceId":"ac36227855e8695c","parentId":"ac36227855e8695c","id":"a70b9cb7da5a8b40","name":"/getrecommendations","timestamp":1614738458130000,"duration":403000,"localEndpoint":{"serviceName":"recommendationservice","ipv4":"192.168.1.180"},"tags":{"http.method":"GET","http.url":"http://recommendationservice/GetRecommendations","load_generator.seq_num":"8630","region":"us-east-1","version":"v234"}}]