[{"traceId":"b0bf2a8260cfd552","parentId":"b0bf2a8260cfd552","id":"b5519f14d13ebdc4","name":"/getrecommendations","timestamp":1614738280396000,"duration":354000,"localEndpoint":{"serviceName":"recommendationservice","ipv4":"192.168.1.180"},"tags":{"http.method":"GET","http.url":"http://recommendationservice/GetRecommendations","load_generator.seq_num":"4816","region":"us-east-1","version":"v234"}},{"traceId":"b0bf2a8260cfd552","parentId":"b5519f14d13ebdc4","id":"42936facddeed6aa","name":"/getproducts","timestamp":1614738280474000,"duration":84000,"localEndpoint":{"serviceName":"productcatalogservice","ipv4":"192.168.1.180"},"tags":{"http.method":"GET","http.url":"http://productcatalogservice/GetProducts","load_generator.seq_num":"4817","region":"us-east-1","version":"v52"}},{"traceId":"b0bf2a8260cfd552","id":"b0bf2a8260cfd552","name":"/cart","timestamp":1614738280344000,"duration":439000,"localEndpoint":{"serviceName":"frontend","ipv4":"192.168.1.180"},"tags":{"http.method":"GET","http.url":"http://frontend/cart","load_generator.seq_num":"4814","region":"us-west-1","version":"v125"}},{"traceId":"b0bf2a8260cfd552","parentId":"b0bf2a8260cfd552","id":"ef5b413db76690c5","name":"/getcart","timestamp":1614738280395000,"duration":98000,"localEndpoint":{"serviceName":"cartservice","ipv4":"192.168.1.180"},"tags":{"http.method":"GET","http.url":"http://cartservice/GetCart","load_generator.seq_num":"4815","region":"us-east-1","version":"v5"}}]