[{"traceId":"b2f145ddf15667f8","parentId":"6f57fa1679a00b6c","id":"6de97eafd18c98fa","name":"/getproducts","timestamp":1614738672526000,"duration":62000,"localEndpoint":{"serviceName":"productcatalogservice","ipv4":"192.168.1.180"},"tags":{"http.method":"GET","http.url":"http://productcatalogservice/GetProducts","load_generator.seq_num":"13220","region":"us-east-1","version":"v52"}},{"traceId":"b2f145ddf15667f8","parentId":"b2f145ddf15667f8","id":"ce2834113f6934ab","name":"/getcart","timestamp":1614738672396000,"duration":124000,"localEndpoint":{"serviceName":"cartservice","ipv4":"192.168.1.180"},"tags":{"http.method":"GET","http.url":"http://cartservice/GetCart","load_generator.seq_num":"13218","region":"us-east-1","version":"v5"}},{"traceId":"b2f145ddf15667f8","id":"b2f145ddf15667f8","name":"/cart","timestamp":1614738672344000,"duration":481000,"localEndpoint":{"serviceName":"frontend","ipv4":"192.168.1.180"},"tags":{"http.method":"GET","http.url":"http://frontend/cart","load_generator.seq_num":"13217","region":"us-east-1","version":"v125"}},{"traceId":"b2f145ddf15667f8","parentId":"b2f145ddf15667f8","id":"6f57fa1679a00b6c","name":"/getrecommendations","timestamp":1614738672398000,"duration":388000,"localEndpoint":{"serviceName":"recommendationservice","ipv4":"192.168.1.180"},"tags":{"http.method":"GET","http.url":"http://recommendationservice/GetRecommendations","load_generator.seq_num":"13219","region":"us-east-1","version":"v234"}}]