[{"traceId":"ca89de367e634366","parentId":"ca89de367e634366","id":"a616c4586e752f2b","name":"/getcart","timestamp":1614738477173000,"duration":28000,"localEndpoint":{"serviceName":"cartservice","ipv4":"192.168.1.180"},"tags":{"http.method":"GET","http.url":"http://cartservice/GetCart","load_generator.seq_num":"9034","region":"us-east-1","version":"v5"}},{"traceId":"ca89de367e634366","parentId":"a8e6f7e4752aee3a","id":"a5299d1f7751b48c","name":"/getproducts","timestamp":1614738477281000,"duration":50000,"localEndpoint":{"serviceName":"productcatalogservice","ipv4":"192.168.1.180"},"tags":{"http.method":"GET","http.url":"http://productcatalogservice/GetProducts","load_generator.seq_num":"9036","region":"us-east-1","version":"v52"}},{"traceId":"ca89de367e634366","id":"ca89de367e634366","name":"/cart","timestamp":1614738477094000,"duration":422000,"localEndpoint":{"serviceName":"frontend","ipv4":"192.168.1.180"},"tags":{"http.method":"GET","http.url":"http://frontend/cart","load_generator.seq_num":"9033","region":"us-west-1","version":"v125"}},{"traceId":"ca89de367e634366","parentId":"ca89de367e634366","id":"a8e6f7e4752aee3a","name":"/getrecommendations","timestamp":1614738477119000,"duration":371000,"localEndpoint":{"serviceName":"recommendationservice","ipv4":"192.168.1.180"},"tags":{"http.method":"GET","http.url":"http://recommendationservice/GetRecommendations","load_generator.seq_num":"9035","region":"us-east-1","version":"v234"}}]