[{"traceId":"dcc54ca0dfca516a","parentId":"dcc54ca0dfca516a","id":"9ad0926f9a0216f3","name":"/adrequest","timestamp":1614738371606000,"duration":108000,"localEndpoint":{"serviceName":"adservice","ipv4":"192.168.1.180"},"tags":{"http.method":"GET","http.url":"http://adservice/AdRequest","load_generator.seq_num":"6776"}},{"traceId":"dcc54ca0dfca516a","id":"dcc54ca0dfca516a","name":"/product","timestamp":1614738371593000,"duration":553000,"localEndpoint":{"serviceName":"frontend","ipv4":"192.168.1.180"},"tags":{"http.method":"GET","http.url":"http://frontend/product","load_generator.seq_num":"6772","region":"us-east-1","starter":"squirtle","version":"v125"}},{"traceId":"dcc54ca0dfca516a","parentId":"dcc54ca0dfca516a","id":"35a29dbe1f9382d3","name":"/getproducts","timestamp":1614738371612000,"duration":31000,"localEndpoint":{"serviceName":"productcatalogservice","ipv4":"192.168.1.180"},"tags":{"http.method":"GET","http.url":"http://productcatalogservice/GetProducts","load_generator.seq_num":"6773","region":"us-east-1","starter":"squirtle","version":"v52"}},{"traceId":"dcc54ca0dfca516a","parentId":"a27f883ace3bb22d","id":"db38f4ae635ff6ad","name":"/getproducts","timestamp":1614738371926000,"duration":96000,"localEndpoint":{"serviceName":"productcatalogservice","ipv4":"192.168.1.180"},"tags":{"http.method":"GET","http.url":"http://productcatalogservice/GetProducts","load_generator.seq_num":"6775","region":"us-east-1","version":"v52"}},{"traceId":"dcc54ca0dfca516a","parentId":"dcc54ca0dfca516a","id":"a27f883ace3bb22d","name":"/getrecommendations","timestamp":1614738371764000,"duration":258000,"localEndpoint":{"serviceName":"recommendationservice","ipv4":"192.168.1.180"},"tags":{"http.method":"GET","http.url":"http://recommendationservice/GetRecommendations","load_generator.seq_num":"6774","region":"us-east-1","version":"v234"}}]