[{"traceId":"e19a7b149d3b7171","id":"e19a7b149d3b7171","name":"/cart","timestamp":1614738069594000,"duration":405000,"localEndpoint":{"serviceName":"frontend","ipv4":"192.168.1.180"},"tags":{"http.method":"GET","http.url":"http://frontend/cart","load_generator.seq_num":"266","region":"us-west-1","version":"v125"}},{"traceId":"e19a7b149d3b7171","parentId":"e19a7b149d3b7171","id":"759f373d29f5d978","name":"/getcart","timestamp":1614738069647000,"duration":128000,"localEndpoint":{"serviceName":"cartservice","ipv4":"192.168.1.180"},"tags":{"http.method":"GET","http.url":"http://cartservice/GetCart","load_generator.seq_num":"267","region":"us-east-1","version":"v5"}},{"traceId":"e19a7b149d3b7171","parentId":"e19a7b149d3b7171","id":"f8ef7782f5d871e7","name":"/getrecommendations","timestamp":1614738069627000,"duration":303000,"localEndpoint":{"serviceName":"recommendationservice","ipv4":"192.168.1.180"},"tags":{"http.method":"GET","http.url":"http://recommendationservice/GetRecommendations","load_generator.seq_num":"268","region":"us-east-1","version":"v234"}},{"traceId":"e19a7b149d3b7171","parentId":"f8ef7782f5d871e7","id":"50ada9bb06a9cc65","name":"/getproducts","timestamp":1614738069799000,"duration":27000,"localEndpoint":{"serviceName":"productcatalogservice","ipv4":"192.168.1.180"},"tags":{"http.method":"GET","http.url":"http://productcatalogservice/GetProducts","load_generator.seq_num":"269","region":"us-east-1","version":"v52"}}]