[{"traceId":"f28472ae39fcc736","parentId":"f28472ae39fcc736","id":"f2be2a59348b5771","name":"/getcart","timestamp":1614738356408000,"duration":87000,"localEndpoint":{"serviceName":"cartservice","ipv4":"192.168.1.180"},"tags":{"http.method":"GET","http.url":"http://cartservice/GetCart","load_generator.seq_num":"6449","region":"us-east-1","version":"v5"}},{"traceId":"f28472ae39fcc736","parentId":"248383c820cf9e45","id":"c562b5355cec6946","name":"/getproducts","timestamp":1614738356501000,"duration":96000,"localEndpoint":{"serviceName":"productcatalogservice","ipv4":"192.168.1.180"},"tags":{"http.method":"GET","http.url":"http://productcatalogservice/GetProducts","load_generator.seq_num":"6451","region":"us-east-1","version":"v52"}},{"traceId":"f28472ae39fcc736","parentId":"f28472ae39fcc736","id":"248383c820cf9e45","name":"/getrecommendations","timestamp":1614738356372000,"duration":359000,"localEndpoint":{"serviceName":"recommendationservice","ipv4":"192.168.1.180"},"tags":{"http.method":"GET","http.url":"http://recommendationservice/GetRecommendations","load_generator.seq_num":"6450","region":"us-east-1","version":"v234"}},{"traceId":"f28472ae39fcc736","id":"f28472ae39fcc736","name":"/cart","timestamp":1614738356344000,"duration":443000,"localEndpoint":{"serviceName":"frontend","ipv4":"192.168.1.180"},"tags":{"http.method":"GET","http.url":"http://frontend/cart","load_generator.seq_num":"6448","region":"us-west-1","version":"v125"}}]