[{"traceId":"f8dc3e67b3292e5a","id":"f8dc3e67b3292e5a","name":"/cart","timestamp":1614738098094000,"duration":176000,"localEndpoint":{"serviceName":"frontend","ipv4":"192.168.1.180"},"tags":{"http.method":"GET","http.url":"http://frontend/cart","load_generator.seq_num":"883","region":"us-east-1","version":"v125"}},{"traceId":"f8dc3e67b3292e5a","parentId":"f8dc3e67b3292e5a","id":"1a3466992c94cda0","name":"/getrecommendations","timestamp":1614738098177000,"duration":91000,"localEndpoint":{"serviceName":"recommendationservice","ipv4":"192.168.1.180"},"tags":{"http.method":"GET","http.url":"http://recommendationservice/GetRecommendations","load_generator.seq_num":"885","region":"us-east-1","version":"v234"}},{"traceId":"f8dc3e67b3292e5a","parentId":"1a3466992c94cda0","id":"3b3de13331a1082a","name":"/getproducts","timestamp":1614738098192000,"duration":2000,"localEndpoint":{"serviceName":"productcatalogservice","ipv4":"192.168.1.180"},"tags":{"http.method":"GET","http.url":"http://productcatalogservice/GetProducts","load_generator.seq_num":"886","region":"us-east-1","version":"v52"}},{"traceId":"f8dc3e67b3292e5a","parentId":"f8dc3e67b3292e5a","id":"b31c14877ce98a51","name":"/getcart","timestamp":1614738098121000,"duration":9000,"localEndpoint":{"serviceName":"cartservice","ipv4":"192.168.1.180"},"tags":{"http.method":"GET","http.url":"http://cartservice/GetCart","load_generator.seq_num":"884","region":"us-east-1","version":"v5"}}]